{"cameraMode":{"drawMode":0,"name":"Shaded","section":"Shading Mode"},"sceneLighting":true,"audioPlay":false,"sceneViewState":{"m_AlwaysRefresh":false,"showFog":true,"showSkybox":true,"showFlares":true,"showImageEffects":true,"showParticleSystems":true,"showVisualEffectGraphs":true,"m_FxEnabled":true},"in2DMode":false,"pivot":{"x":72.20579528808594,"y":-65.99893951416016,"z":104.55307006835938},"rotation":{"x":-0.2302813082933426,"y":-0.27378049492836,"z":0.06774620711803436,"w":-0.9313905835151672},"size":72.93000030517578,"orthographic":false}